odoo/addons/sale_project_key/LICENSE
odoo/addons/sale_project_key/README.rst
odoo/addons/sale_project_key/__init__.py
odoo/addons/sale_project_key/__manifest__.py
odoo/addons/sale_project_key/images/screen.png
odoo/addons/sale_project_key/models/__init__.py
odoo/addons/sale_project_key/models/sale_order_line.py
odoo/addons/sale_project_key/readme/CONTRIBUTORS.md
odoo/addons/sale_project_key/readme/DESCRIPTION.md
odoo/addons/sale_project_key/readme/USAGE.md
odoo/addons/sale_project_key/static/description/icon.png
odoo/addons/sale_project_key/static/description/index.html
odoo/addons/sale_project_key/views/sale_order_views.xml
odoo_addon_sale_project_key-16.0.1.0.0.dist-info/METADATA
odoo_addon_sale_project_key-16.0.1.0.0.dist-info/WHEEL
odoo_addon_sale_project_key-16.0.1.0.0.dist-info/top_level.txt
odoo_addon_sale_project_key-16.0.1.0.0.dist-info/RECORD
